{"cameraMode":{"drawMode":0,"name":"Shaded","section":"Shading Mode"},"sceneLighting":true,"audioPlay":false,"sceneViewState":{"m_AlwaysRefresh":false,"showFog":true,"showSkybox":true,"showFlares":true,"showImageEffects":true,"showParticleSystems":true,"showVisualEffectGraphs":true,"m_FxEnabled":true},"in2DMode":false,"pivot":{"x":2.185357093811035,"y":1.0192586183547974,"z":0.6423543691635132},"rotation":{"x":0.14494836330413819,"y":0.6660846471786499,"z":-0.13430464267730714,"w":0.7193182706832886},"size":0.8003905415534973,"orthographic":false}